my_pytest_plugin/__init__.py
my_pytest_plugin/my_pytest_plugin.py
tests/__init__.py
tests/test_my_plugin.py
my_pytest_plugin-0.1.dist-info/METADATA
my_pytest_plugin-0.1.dist-info/WHEEL
my_pytest_plugin-0.1.dist-info/entry_points.txt
my_pytest_plugin-0.1.dist-info/top_level.txt
my_pytest_plugin-0.1.dist-info/RECORD
