Metadata-Version: 2.1
Name: my-pytest-plugin
Version: 0.1
Requires-Dist: pytest
